markdown/__init__.py
markdown/__main__.py
markdown/__meta__.py
markdown/blockparser.py
markdown/blockprocessors.py
markdown/core.py
markdown/htmlparser.py
markdown/inlinepatterns.py
markdown/postprocessors.py
markdown/preprocessors.py
markdown/serializers.py
markdown/test_tools.py
markdown/treeprocessors.py
markdown/util.py
markdown/extensions/__init__.py
markdown/extensions/abbr.py
markdown/extensions/admonition.py
markdown/extensions/attr_list.py
markdown/extensions/codehilite.py
markdown/extensions/def_list.py
markdown/extensions/extra.py
markdown/extensions/fenced_code.py
markdown/extensions/footnotes.py
markdown/extensions/legacy_attrs.py
markdown/extensions/legacy_em.py
markdown/extensions/md_in_html.py
markdown/extensions/meta.py
markdown/extensions/nl2br.py
markdown/extensions/sane_lists.py
markdown/extensions/smarty.py
markdown/extensions/tables.py
markdown/extensions/toc.py
markdown/extensions/wikilinks.py
Markdown-3.5.2.dist-info/LICENSE.md
Markdown-3.5.2.dist-info/METADATA
Markdown-3.5.2.dist-info/WHEEL
Markdown-3.5.2.dist-info/entry_points.txt
Markdown-3.5.2.dist-info/top_level.txt
Markdown-3.5.2.dist-info/RECORD
