Metadata-Version: 2.1
Name: Markdown
Version: 3.5.2
Summary: Python implementation of John Gruber's Markdown.
Author: Manfred Stienstra, Yuri Takhteyev
Author-email: Waylan limberg <python.markdown@gmail.com>
Maintainer: Isaac Muse
Maintainer-email: Waylan Limberg <python.markdown@gmail.com>
License: Copyright 2007, 2008 The Python Markdown Project (v. 1.7 and later)
Project-URL: Homepage, https://Python-Markdown.github.io/
Project-URL: Documentation, https://Python-Markdown.github.io/
Project-URL: Repository, https://github.com/Python-Markdown/markdown
Project-URL: Issue Tracker, https://github.com/Python-Markdown/markdown/issues
Project-URL: Changelog, https://python-markdown.github.io/changelog/
Keywords: markdown,markdown-parser,python-markdown,markdown-to-html
Classifier: Development Status :: 5 - Production/Stable
Classifier: License :: OSI Approved :: BSD License
Classifier: Operating System :: OS Independent
Classifier: Programming Language :: Python
Classifier: Programming Language :: Python :: 3
Classifier: Programming Language :: Python :: 3.8
Classifier: Programming Language :: Python :: 3.9
Classifier: Programming Language :: Python :: 3.10
Classifier: Programming Language :: Python :: 3.11
Classifier: Programming Language :: Python :: 3.12
Classifier: Programming Language :: Python :: 3 :: Only
Classifier: Programming Language :: Python :: Implementation :: CPython
Classifier: Programming Language :: Python :: Implementation :: PyPy
Classifier: Topic :: Communications :: Email :: Filters
Classifier: Topic :: Internet :: WWW/HTTP :: Dynamic Content :: CGI Tools/Libraries
Classifier: Topic :: Internet :: WWW/HTTP :: Site Management
Classifier: Topic :: Software Development :: Documentation
Classifier: Topic :: Software Development :: Libraries :: Python Modules
Classifier: Topic :: Text Processing :: Filters
Classifier: Topic :: Text Processing :: Markup :: HTML
Classifier: Topic :: Text Processing :: Markup :: Markdown
Requires-Python: >=3.8
License-File: LICENSE.md
Requires-Dist: importlib-metadata>=4.4; python_version < "3.10"
Provides-Extra: testing
Requires-Dist: coverage; extra == "testing"
Requires-Dist: pyyaml; extra == "testing"
Provides-Extra: docs
Requires-Dist: mkdocs>=1.5; extra == "docs"
Requires-Dist: mkdocs-nature>=0.6; extra == "docs"
Requires-Dist: mdx_gh_links>=0.2; extra == "docs"
Requires-Dist: mkdocstrings[python]; extra == "docs"
Requires-Dist: mkdocs-gen-files; extra == "docs"
Requires-Dist: mkdocs-section-index; extra == "docs"
Requires-Dist: mkdocs-literate-nav; extra == "docs"
